rexa/__init__.py
rexa/conversion.py
rexa/extraction.py
rexa/formatting.py
rexa/regex_mapper.py
rexa/texttools.py
rexa/validation.py
rexa-1.0.4.dist-info/licenses/LICENSE.txt
rexa-1.0.4.dist-info/METADATA
rexa-1.0.4.dist-info/WHEEL
rexa-1.0.4.dist-info/top_level.txt
rexa-1.0.4.dist-info/RECORD
