Metadata-Version: 2.4
Name: rexa
Version: 1.0.4
Summary: A powerful regex and NLP utility library for text validation, extraction, conversion, formatting, and pattern generation.
Author-email: Arshia Saberian <arshia82sbn@gmail.com>
License: MIT
Project-URL: Homepage, https://github.com/arshia82sbn/rexa
Project-URL: Documentation, https://rexa.readthedocs.io/
Project-URL: Repository, https://github.com/arshia82sbn/rexa
Project-URL: Issues, https://github.com/arshia82sbn/rexa/issues
Keywords: regex,nlp,text-processing,validation,extraction,formatting
Classifier: Programming Language :: Python :: 3
Classifier: Programming Language :: Python :: 3.10
Classifier: Programming Language :: Python :: 3.11
Classifier: Operating System :: OS Independent
Classifier: Intended Audience :: Developers
Classifier: Topic :: Software Development :: Libraries :: Python Modules
Classifier: Topic :: Text Processing :: Linguistic
Classifier: License :: OSI Approved :: MIT License
Requires-Python: >=3.10
License-File: LICENSE.txt
Requires-Dist: regex>=2023.10.3
Requires-Dist: dateparser>=1.1.8
Requires-Dist: pydantic>=2.0.0
Requires-Dist: nltk>=3.8.1
Requires-Dist: langdetect>=1.0.9
Dynamic: license-file
